LICENSE.txt
MANIFEST.in
README.rst
ecglist.py
setup.py
email_ecglist.egg-info/PKG-INFO
email_ecglist.egg-info/SOURCES.txt
email_ecglist.egg-info/dependency_links.txt
email_ecglist.egg-info/top_level.txt