Metadata-Version: 1.1
Name: email-ecglist
Version: 1.6
Summary: Check email addresses against the austrian do-not-email list (ECG-Liste)
Home-page: http://github.com/mjl/email-ecglist
Author: Martin J. Laubach
Author-email: pypi+ecglist@laubach.at
License: BSD
Keywords: email validation ecglist
Platform: UNKNOWN
Classifier: Development Status :: 5 - Production/Stable
Classifier: Topic :: Communications :: Email
Classifier: Intended Audience :: Developers
Classifier: License :: OSI Approved :: BSD License
Classifier: Operating System :: OS Independent
Classifier: Programming Language :: Python
Classifier: Programming Language :: Python :: 3
